torchio/__init__.py
torchio/cli/__init__.py
torchio/cli/apply_transform.py
torchio/cli/print_info.py
torchio/constants.py
torchio/data/__init__.py
torchio/data/dataset.py
torchio/data/image.py
torchio/data/inference/__init__.py
torchio/data/inference/aggregator.py
torchio/data/io.py
torchio/data/loader.py
torchio/data/queue.py
torchio/data/sampler/__init__.py
torchio/data/sampler/grid.py
torchio/data/sampler/label.py
torchio/data/sampler/sampler.py
torchio/data/sampler/uniform.py
torchio/data/sampler/weighted.py
torchio/data/subject.py
torchio/datasets/__init__.py
torchio/datasets/bite.py
torchio/datasets/ct_rate.py
torchio/datasets/episurg.py
torchio/datasets/fpg.py
torchio/datasets/itk_snap/__init__.py
torchio/datasets/itk_snap/itk_snap.py
torchio/datasets/ixi.py
torchio/datasets/medmnist.py
torchio/datasets/mni/__init__.py
torchio/datasets/mni/colin.py
torchio/datasets/mni/icbm.py
torchio/datasets/mni/mni.py
torchio/datasets/mni/pediatric.py
torchio/datasets/mni/sheep.py
torchio/datasets/rsna_miccai.py
torchio/datasets/rsna_spine_fracture.py
torchio/datasets/slicer.py
torchio/datasets/zone_plate.py
torchio/download.py
torchio/external/__init__.py
torchio/external/due.py
torchio/external/imports.py
torchio/py.typed
torchio/reference.py
torchio/transforms/__init__.py
torchio/transforms/augmentation/__init__.py
torchio/transforms/augmentation/composition.py
torchio/transforms/augmentation/intensity/__init__.py
torchio/transforms/augmentation/intensity/random_bias_field.py
torchio/transforms/augmentation/intensity/random_blur.py
torchio/transforms/augmentation/intensity/random_gamma.py
torchio/transforms/augmentation/intensity/random_ghosting.py
torchio/transforms/augmentation/intensity/random_labels_to_image.py
torchio/transforms/augmentation/intensity/random_motion.py
torchio/transforms/augmentation/intensity/random_noise.py
torchio/transforms/augmentation/intensity/random_spike.py
torchio/transforms/augmentation/intensity/random_swap.py
torchio-0.21.2.dist-info/WHEEL
torchio-0.21.2.dist-info/entry_points.txt
torchio-0.21.2.dist-info/METADATA
torchio-0.21.2.dist-info/RECORD
