Metadata-Version: 2.3
Name: torchio
Version: 0.21.2
Summary: Tools for medical image processing with PyTorch
Keywords: medical,image processing,pytorch,augmentation,mri
Author: TorchIO contributors
Classifier: Development Status :: 4 - Beta
Classifier: Environment :: Console
Classifier: Intended Audience :: Science/Research
Classifier: License :: OSI Approved :: Apache Software License
Classifier: Natural Language :: English
Classifier: Operating System :: OS Independent
Classifier: Programming Language :: Python
Classifier: Programming Language :: Python :: 3
Classifier: Programming Language :: Python :: 3 :: Only
Classifier: Programming Language :: Python :: 3.10
Classifier: Programming Language :: Python :: 3.11
Classifier: Programming Language :: Python :: 3.12
Classifier: Programming Language :: Python :: 3.13
Classifier: Topic :: Scientific/Engineering
Classifier: Topic :: Scientific/Engineering :: Artificial Intelligence
Classifier: Topic :: Scientific/Engineering :: Image Processing
Classifier: Topic :: Scientific/Engineering :: Medical Science Apps.
Classifier: Typing :: Typed
Requires-Dist: deprecated>=1.2
Requires-Dist: einops>=0.3
Requires-Dist: humanize>=0.1
Requires-Dist: nibabel>=3
Requires-Dist: numpy>=1.20
Requires-Dist: packaging>=20
Requires-Dist: rich>=10
Requires-Dist: scipy>=1.7
Requires-Dist: simpleitk>=1.3,!=2.0.*,!=2.1.1.1
Requires-Dist: torch>=1.9
Requires-Dist: tqdm>=4.40
Requires-Dist: typer>=0.1
Requires-Dist: pandas>=1 ; extra == 'csv'
Requires-Dist: colorcet ; extra == 'plot'
Requires-Dist: matplotlib>=3.4 ; extra == 'plot'
Requires-Dist: scikit-learn>=1.6.1 ; extra == 'sklearn'
Requires-Dist: ffmpeg-python>=0.2.0 ; extra == 'video'
Maintainer: Fernando Perez-Garcia
Maintainer-email: Fernando Perez-Garcia <fepegar@gmail.com>
Requires-Python: >=3.10
Project-URL: Homepage, https://torchio.org
Project-URL: Source, https://github.com/TorchIO-project/torchio
Project-URL: Issue tracker, https://github.com/TorchIO-project/torchio/issues
Project-URL: Documentation, https://docs.torchio.org
Project-URL: Release notes, https://github.com/TorchIO-project/torchio/releases
Provides-Extra: csv
Provides-Extra: plot
Provides-Extra: sklearn
Provides-Extra: video
